sql_querystring_builder/__init__.py
sql_querystring_builder/abstract_clause.py
sql_querystring_builder/clauses.py
sql_querystring_builder/query_builder.py
sql_querystring_builder/tables.py
sql_querystring_builder-0.0.3.post1.dist-info/LICENSE
sql_querystring_builder-0.0.3.post1.dist-info/METADATA
sql_querystring_builder-0.0.3.post1.dist-info/WHEEL
sql_querystring_builder-0.0.3.post1.dist-info/top_level.txt
sql_querystring_builder-0.0.3.post1.dist-info/RECORD
