Metadata-Version: 2.1
Name: sql_querystring_builder
Version: 0.0.3.post1
Summary: Wraps string building of MS SQL queries
Author-email: Wael GRIBAA <g.wael@outlook.fr>
License: GNU GENERAL PUBLIC LICENSE
Keywords: sql,query,string
Classifier: Programming Language :: Python :: 3
Classifier: License :: OSI Approved :: GNU General Public License v3 (GPLv3)
Classifier: Operating System :: OS Independent
Requires-Python: >=3.7
License-File: LICENSE
